cuda/__init__.py
cuda_py-1.0.2.dist-info/LICENSE
cuda_py-1.0.2.dist-info/METADATA
cuda_py-1.0.2.dist-info/WHEEL
cuda_py-1.0.2.dist-info/top_level.txt
cuda_py-1.0.2.dist-info/RECORD
