Metadata-Version: 2.1
Name: cuda-py
Version: 1.0.2
Summary: A very simple python wrapper for running code on CUDA devices.
Author-email: GloriousGlider8 <sam.g.plimmer@gmail.com>
Classifier: Programming Language :: Python :: 3
Classifier: License :: OSI Approved :: MIT License
Classifier: Operating System :: OS Independent
Requires-Python: >=3.8
License-File: LICENSE
